[{"name": "face_bounds.FaceBounds.peakmem_face_bounds", "idx": 0, "pretty_name": "face_bounds.FaceBounds.peakmem_face_bounds(PosixPath('/home/runner/work/uxarray/uxarray/test/meshfiles/ugrid/quad-hexagon/grid.nc'))", "last_rev": 3830, "last_value": 280178688.0, "last_err": 0.0, "prev_value": 277946368.0, "change_rev": [3808, 3830]}, {"name": "face_bounds.FaceBounds.peakmem_face_bounds", "idx": 1, "pretty_name": "face_bounds.FaceBounds.peakmem_face_bounds(PosixPath('/home/runner/work/uxarray/uxarray/test/meshfiles/ugrid/geoflow-small/grid.nc'))", "last_rev": 3830, "last_value": 281948160.0, "last_err": 0.0, "prev_value": 279576576.0, "change_rev": [3808, 3830]}, {"name": "face_bounds.FaceBounds.peakmem_face_bounds", "idx": 2, "pretty_name": "face_bounds.FaceBounds.peakmem_face_bounds(PosixPath('/home/runner/work/uxarray/uxarray/test/meshfiles/scrip/outCSne8/outCSne8.nc'))", "last_rev": 3830, "last_value": 279035904.0, "last_err": 0.0, "prev_value": 276795392.0, "change_rev": [3808, 3830]}, {"name": "face_bounds.FaceBounds.peakmem_face_bounds", "idx": 3, "pretty_name": "face_bounds.FaceBounds.peakmem_face_bounds(PosixPath('/home/runner/work/uxarray/uxarray/test/meshfiles/mpas/QU/oQU480.231010.nc'))", "last_rev": 3830, "last_value": 230092800.0, "last_err": 0.0, "prev_value": 227946496.0, "change_rev": [3808, 3830]}, {"name": "face_bounds.FaceBounds.time_face_bounds", "idx": 0, "pretty_name": "face_bounds.FaceBounds.time_face_bounds(PosixPath('/home/runner/work/uxarray/uxarray/test/meshfiles/ugrid/quad-hexagon/grid.nc'))", "last_rev": 3830, "last_value": 0.07362399999996683, "last_err": 0.00010644904814687787, "prev_value": 3.8049729203160895e-05, "change_rev": [3802, 3808]}, {"name": "face_bounds.FaceBounds.time_face_bounds", "idx": 1, "pretty_name": "face_bounds.FaceBounds.time_face_bounds(PosixPath('/home/runner/work/uxarray/uxarray/test/meshfiles/ugrid/geoflow-small/grid.nc'))", "last_rev": 3830, "last_value": 18.041403072000094, "last_err": 0.8980019379236768, "prev_value": null, "change_rev": null}, {"name": "face_bounds.FaceBounds.time_face_bounds", "idx": 2, "pretty_name": "face_bounds.FaceBounds.time_face_bounds(PosixPath('/home/runner/work/uxarray/uxarray/test/meshfiles/scrip/outCSne8/outCSne8.nc'))", "last_rev": 3830, "last_value": 1.8822368300000107, "last_err": 0.0900283758677217, "prev_value": null, "change_rev": null}, {"name": "face_bounds.FaceBounds.time_face_bounds", "idx": 3, "pretty_name": "face_bounds.FaceBounds.time_face_bounds(PosixPath('/home/runner/work/uxarray/uxarray/test/meshfiles/mpas/QU/oQU480.231010.nc'))", "last_rev": 3830, "last_value": 14.367158771499987, "last_err": 0.03685072135775236, "prev_value": 12.45588256549999, "change_rev": [3737, 3748]}, {"name": "import.Imports.timeraw_import_uxarray", "idx": null, "pretty_name": "import.Imports.timeraw_import_uxarray", "last_rev": 3830, "last_value": 1.4006617574999893, "last_err": 0.13687769457299037, "prev_value": null, "change_rev": null}, {"name": "mpas_ocean.ConnectivityConstruction.time_n_nodes_per_face", "idx": 0, "pretty_name": "mpas_ocean.ConnectivityConstruction.time_n_nodes_per_face('480km')", "last_rev": 3830, "last_value": 5.369066540901749e-06, "last_err": 7.185807808077248e-08, "prev_value": null, "change_rev": null}, {"name": "mpas_ocean.ConnectivityConstruction.time_n_nodes_per_face", "idx": 1, "pretty_name": "mpas_ocean.ConnectivityConstruction.time_n_nodes_per_face('120km')", "last_rev": 3830, "last_value": 5.775785714310351e-06, "last_err": 7.872951652405907e-08, "prev_value": null, "change_rev": null}, {"name": "mpas_ocean.GeoDataFrame.peakmem_to_geodataframe", "idx": 0, "pretty_name": "mpas_ocean.GeoDataFrame.peakmem_to_geodataframe('480km', True)", "last_rev": 3830, "last_value": 303153152.0, "last_err": 0.0, "prev_value": 300701696.0, "change_rev": [3808, 3830]}, {"name": "mpas_ocean.GeoDataFrame.peakmem_to_geodataframe", "idx": 1, "pretty_name": "mpas_ocean.GeoDataFrame.peakmem_to_geodataframe('480km', False)", "last_rev": 3830, "last_value": 301838336.0, "last_err": 262575.15789473685, "prev_value": 290713600.0, "change_rev": [3592, 3598]}, {"name": "mpas_ocean.GeoDataFrame.peakmem_to_geodataframe", "idx": 2, "pretty_name": "mpas_ocean.GeoDataFrame.peakmem_to_geodataframe('120km', True)", "last_rev": 3830, "last_value": 329011200.0, "last_err": 1161108.2105263157, "prev_value": 317366272.0, "change_rev": [3592, 3598]}, {"name": "mpas_ocean.GeoDataFrame.peakmem_to_geodataframe", "idx": 3, "pretty_name": "mpas_ocean.GeoDataFrame.peakmem_to_geodataframe('120km', False)", "last_rev": 3830, "last_value": 349982720.0, "last_err": 1402987.7894736843, "prev_value": 338075648.0, "change_rev": [3592, 3598]}, {"name": "mpas_ocean.GeoDataFrame.time_to_geodataframe", "idx": 0, "pretty_name": "mpas_ocean.GeoDataFrame.time_to_geodataframe('480km', True)", "last_rev": 3830, "last_value": 0.005326144499804286, "last_err": 0.0001253807290212568, "prev_value": null, "change_rev": null}, {"name": "mpas_ocean.GeoDataFrame.time_to_geodataframe", "idx": 1, "pretty_name": "mpas_ocean.GeoDataFrame.time_to_geodataframe('480km', False)", "last_rev": 3830, "last_value": 0.09286138750030659, "last_err": 0.001044271828675536, "prev_value": null, "change_rev": null}, {"name": "mpas_ocean.GeoDataFrame.time_to_geodataframe", "idx": 2, "pretty_name": "mpas_ocean.GeoDataFrame.time_to_geodataframe('120km', True)", "last_rev": 3830, "last_value": 0.055171140500078764, "last_err": 0.00048264648011274447, "prev_value": null, "change_rev": null}, {"name": "mpas_ocean.GeoDataFrame.time_to_geodataframe", "idx": 3, "pretty_name": "mpas_ocean.GeoDataFrame.time_to_geodataframe('120km', False)", "last_rev": 3830, "last_value": 1.1754749154997626, "last_err": 0.00972269289863831, "prev_value": null, "change_rev": null}, {"name": "mpas_ocean.Gradient.peakmem_gradient", "idx": 0, "pretty_name": "mpas_ocean.Gradient.peakmem_gradient('480km')", "last_rev": 3830, "last_value": 229220352.0, "last_err": 183673.26315789475, "prev_value": 217743360.0, "change_rev": [3592, 3598]}, {"name": "mpas_ocean.Gradient.peakmem_gradient", "idx": 1, "pretty_name": "mpas_ocean.Gradient.peakmem_gradient('120km')", "last_rev": 3830, "last_value": 249200640.0, "last_err": 621082.947368421, "prev_value": 237670400.0, "change_rev": [3592, 3598]}, {"name": "mpas_ocean.Gradient.time_gradient", "idx": 0, "pretty_name": "mpas_ocean.Gradient.time_gradient('480km')", "last_rev": 3830, "last_value": 0.00029295987179722986, "last_err": 2.941445714015792e-06, "prev_value": 0.00033727532351857754, "change_rev": [3398, 3405]}, {"name": "mpas_ocean.Gradient.time_gradient", "idx": 1, "pretty_name": "mpas_ocean.Gradient.time_gradient('120km')", "last_rev": 3830, "last_value": 0.002812009624960865, "last_err": 1.4772387047348222e-05, "prev_value": 0.0028680908750402523, "change_rev": [3416, 3418]}, {"name": "mpas_ocean.Integrate.peakmem_integrate", "idx": 0, "pretty_name": "mpas_ocean.Integrate.peakmem_integrate('480km')", "last_rev": 3830, "last_value": 280395776.0, "last_err": 0.0, "prev_value": 277987328.0, "change_rev": [3808, 3830]}, {"name": "mpas_ocean.Integrate.peakmem_integrate", "idx": 1, "pretty_name": "mpas_ocean.Integrate.peakmem_integrate('120km')", "last_rev": 3830, "last_value": 296501248.0, "last_err": 434176.0, "prev_value": 252088320.0, "change_rev": [3802, 3808]}, {"name": "mpas_ocean.Integrate.time_integrate", "idx": 0, "pretty_name": "mpas_ocean.Integrate.time_integrate('480km')", "last_rev": 3830, "last_value": 0.0132162514999834, "last_err": 0.00011718934631029493, "prev_value": 1.7170374949999996, "change_rev": [3802, 3808]}, {"name": "mpas_ocean.Integrate.time_integrate", "idx": 1, "pretty_name": "mpas_ocean.Integrate.time_integrate('120km')", "last_rev": 3830, "last_value": 0.187670586500019, "last_err": 0.0016603680462843947, "prev_value": 0.22082160200011458, "change_rev": [3802, 3808]}, {"name": "quad_hexagon.QuadHexagon.mem_open_dataset", "idx": null, "pretty_name": "quad_hexagon.QuadHexagon.mem_open_dataset", "last_rev": 3830, "last_value": 1704.0, "last_err": 0.0, "prev_value": 1768.0, "change_rev": [3802, 3808]}, {"name": "quad_hexagon.QuadHexagon.mem_open_grid", "idx": null, "pretty_name": "quad_hexagon.QuadHexagon.mem_open_grid", "last_rev": 3830, "last_value": 336.0, "last_err": 0.0, "prev_value": null, "change_rev": null}, {"name": "quad_hexagon.QuadHexagon.peakmem_open_dataset", "idx": null, "pretty_name": "quad_hexagon.QuadHexagon.peakmem_open_dataset", "last_rev": 3830, "last_value": 212668416.0, "last_err": 7247189.333333333, "prev_value": null, "change_rev": null}, {"name": "quad_hexagon.QuadHexagon.peakmem_open_grid", "idx": null, "pretty_name": "quad_hexagon.QuadHexagon.peakmem_open_grid", "last_rev": 3830, "last_value": 226967552.0, "last_err": 0.0, "prev_value": 224759808.0, "change_rev": [3808, 3830]}, {"name": "quad_hexagon.QuadHexagon.time_open_dataset", "idx": null, "pretty_name": "quad_hexagon.QuadHexagon.time_open_dataset", "last_rev": 3830, "last_value": 0.006818768249900131, "last_err": 4.5954992699896685e-05, "prev_value": 0.006322208749992342, "change_rev": [3507, 3516]}, {"name": "quad_hexagon.QuadHexagon.time_open_grid", "idx": null, "pretty_name": "quad_hexagon.QuadHexagon.time_open_grid", "last_rev": 3830, "last_value": 0.005671397249983556, "last_err": 0.00022115711856249593, "prev_value": null, "change_rev": null}]